_other/_legacy/CCF30_to_gubra.py
_other/_legacy/gubra_to_CCF30.py
_other/_legacy/gubra_to_CCF50.py
_other/_testing/_test.py
_other/_testing/_test2.py
_other/_testing/_test3.py
_other/drafts/360_animation.py
_other/drafts/ANOVA_draft.py
_other/drafts/cluster_ttests.py
_other/drafts/collapse_atlas.py
_other/drafts/cstats_adding_stats_options.py
_other/drafts/csv_to_nii.py
_other/drafts/ez_thr.py
_other/drafts/filter_objects_by_size.py
_other/drafts/fsleyes.py
_other/drafts/h5_to_tifs_batch.py
_other/drafts/img_stats_draft.py
_other/drafts/load_czi_subset.py
_other/drafts/native_cluster_crop.py
_other/drafts/native_cluster_crop_legacy.py
_other/drafts/native_clusters_crop.py
_other/drafts/native_clusters_mean_IF_in_seg.py
_other/drafts/nii_to_csv.py
_other/drafts/prep_ilastik_h5.py
_other/drafts/rstats_mean_IF_summary_v2.py
_other/drafts/setup.py
_other/drafts/sexes_to_cluster_densities_csv.py
_other/drafts/volcano.py
_other/drafts/_ABCA/CCF30_to_MERFISH30.py
_other/drafts/_ABCA/RNAseq_dot_plot.py
_other/drafts/_ABCA/RNAseq_dot_plot_based_on_merfish_dot_plot.py
_other/drafts/_ABCA/RNAseq_expression_in_cell_types.py
_other/drafts/_ABCA/RNAseq_expression_in_mice.py
_other/drafts/_ABCA/RNAseq_expression_in_mice_heatmap.py
_other/drafts/_ABCA/RNAseq_expression_in_mice_neurons_astro_ug.py
_other/drafts/_ABCA/RNAseq_expression_in_mouse_MSNs.py
_other/drafts/_ABCA/RNAseq_expression_in_mouse_cells_test.py
_other/drafts/_ABCA/RNAseq_expression_in_neurons_astro_ug.py
_other/drafts/_ABCA/correlation_comparison.py
_other/drafts/_ABCA/correlation_parallel.py
_other/drafts/_ABCA/correlation_parallel_to_nii.py
_other/drafts/_ABCA/correlation_permutation.py
_other/drafts/_ABCA/correlation_plot.py
_other/drafts/_ABCA/merfish_dot_plot.py
_other/drafts/_ABCA/merfish_dot_plot_legend.py
_other/drafts/_ABCA/merfish_filter_expression.py
_other/drafts/_ABCA/merfish_heatmap.py
_other/drafts/_ABCA/merfish_imputed_genes.py
_other/drafts/_ABCA/merfish_resample.py
heifetslab_unravel-1.0.0b12.dist-info/METADATA
heifetslab_unravel-1.0.0b12.dist-info/WHEEL
heifetslab_unravel-1.0.0b12.dist-info/entry_points.txt
heifetslab_unravel-1.0.0b12.dist-info/top_level.txt
heifetslab_unravel-1.0.0b12.dist-info/RECORD
