Metadata-Version: 2.4
Name: heifetslab-unravel
Version: 1.0.0b12
Summary: UNRAVEL: UN-biased high-Resolution Analysis and Validation of Ensembles using Light sheet images
Author-email: Daniel Ryskamp Rijsketic <danrijs@stanford.edu>, Austen Brooks Casey <abcasey@stanford.edu>, Boris Dov Heifets <bheifets@stanford.edu>
Maintainer-email: Daniel Ryskamp Rijsketic <danrijs@stanford.edu>
License-Expression: GPL-3.0-or-later
Project-URL: Homepage, https://github.com/b-heifets/UNRAVEL
Project-URL: Documentation, https://b-heifets.github.io/UNRAVEL/
Keywords: neuroscience,image analysis,light sheet microscopy,brain mapping,data analysis,voxel-wise analysis,cell density quantification
Classifier: Development Status :: 4 - Beta
Classifier: Intended Audience :: Developers
Classifier: Intended Audience :: Science/Research
Classifier: Programming Language :: Python
Classifier: Programming Language :: Python :: 3
Classifier: Programming Language :: Python :: 3.11
Classifier: Topic :: Scientific/Engineering :: Bio-Informatics
Classifier: Topic :: Scientific/Engineering :: Medical Science Apps.
Requires-Dist: aicspylibczi<4.0.0,>=3.1.2
Requires-Dist: antspyx<1.0.0,>=0.4.2
Requires-Dist: boto3==1.28.17
Requires-Dist: botocore==1.31.17
Requires-Dist: connected_components_3d<4.0.0,>=3.24.0
Requires-Dist: czifile<2020.0.0,>=2019.7.2
Requires-Dist: dask<2024.0.0,>=2023.4.1
Requires-Dist: fslpy<4.0.0,>=3.18.2
Requires-Dist: h5py<4.0.0,>=3.8.0
Requires-Dist: lxml<5.0.0,>=4.9.3
Requires-Dist: matplotlib<4.0.0,>=3.7.1
Requires-Dist: nibabel<6.0.0,>=5.2.1
Requires-Dist: numpy==1.24.4
Requires-Dist: opencv_python<5.0.0,>=4.7.0.72
Requires-Dist: openpyxl<4.0.0,>=3.1.2
Requires-Dist: pandas<2.0.0,>=1.5.3
Requires-Dist: rich<14.0.0,>=13.7.1
Requires-Dist: rich_argparse<2.0.0,>=1.4.0
Requires-Dist: s3transfer==0.6.1
Requires-Dist: scipy<2.0.0,>=1.13.1
Requires-Dist: seaborn<1.0.0,>=0.13.2
Requires-Dist: setuptools>=77.0.0
Requires-Dist: statsmodels<1.0.0,>=0.14.0
Requires-Dist: termcolor<3.0.0,>=2.4.0
Requires-Dist: tifffile<2024.0.0,>=2023.8.30
Requires-Dist: zarr<3.0.0,>=2.14.2
Provides-Extra: dev
Requires-Dist: myst-parser; extra == "dev"
Requires-Dist: python-cfonts; extra == "dev"
Requires-Dist: pydata_sphinx_theme; extra == "dev"
Requires-Dist: sphinx; extra == "dev"
Requires-Dist: sphinx-autobuild; extra == "dev"
Requires-Dist: sphinx-togglebutton; extra == "dev"
Requires-Dist: sphinx-design; extra == "dev"
Requires-Dist: sphinxcontrib-mermaid; extra == "dev"
Requires-Dist: build; extra == "dev"
Requires-Dist: twine; extra == "dev"
